numerica/__init__.py
numerica/__main__.py
numerica/differentiation/__init__.py
numerica/differentiation/euler/__init__.py
numerica/differentiation/euler/backward.py
numerica/differentiation/euler/forward.py
numerica/differentiation/euler/midpoint.py
numerica/finite_differences/__init__.py
numerica/finite_differences/degree.py
numerica/integration/__init__.py
numerica/integration/simpson.py
numerica/integration/trapezoidal.py
numerica/interpolation/__init__.py
numerica/interpolation/lagrange.py
numerica/linear_systems/__init__.py
numerica/linear_systems/gauss.py
numerica/linear_systems/gaussseidel.py
numerica/linear_systems/jacobi.py
numerica/matrix/__init__.py
numerica/matrix/define.py
numerica/matrix/operations.py
numerica/matrix/inverse/__init__.py
numerica/matrix/inverse/gaussjordan.py
numerica/nonlinear/__init__.py
numerica/nonlinear/bracketing/__init__.py
numerica/nonlinear/bracketing/bisection.py
numerica/nonlinear/bracketing/graph.py
numerica/nonlinear/bracketing/regulafalsi.py
numerica/nonlinear/iterative/__init__.py
numerica/nonlinear/iterative/fixedpoint.py
numerica/nonlinear/iterative/newtonraphson.py
numerica/nonlinear/iterative/secant.py
numerica/regression/__init__.py
numerica/regression/leastsquares.py
numerica/utils/__init__.py
numerica/utils/function.py
numerica/utils/math.py
numerica-0.3.1.dist-info/LICENSE
numerica-0.3.1.dist-info/METADATA
numerica-0.3.1.dist-info/WHEEL
numerica-0.3.1.dist-info/top_level.txt
numerica-0.3.1.dist-info/RECORD
