Metadata-Version: 2.1
Name: numerica
Version: 0.3.1
Summary: Numerical Analysis methods with Python (experimental)
Home-page: http://github.com/ramesaliyev/numerica
Author: Rames Aliyev
Author-email: creator@ramesaliyev.com
License: MIT
Platform: UNKNOWN
